[{"Id":3,"Name":"staasaddassdsdring","Email":"useaasddassdadsr@adsexample.com","Address":null,"Laptop":null,"LibraryId":null,"Money":0,"Age":0,"Library":null,"Universities":[],"CourseStudents":[]},{"Id":2,"Name":"staasdsdring","Email":"useasdadsr@adsexample.com","Address":null,"Laptop":null,"LibraryId":null,"Money":0,"Age":0,"Library":null,"Universities":[],"CourseStudents":[]},{"Id":1,"Name":"stasdring","Email":"user@adsexample.com","Address":null,"Laptop":null,"LibraryId":null,"Money":0,"Age":0,"Library":null,"Universities":[],"CourseStudents":[]},{"Id":0,"Name":"stradsasdasddasdasing","Email":"usdsaasdasddaser@example.com","Address":null,"Laptop":null,"LibraryId":null,"Money":0,"Age":0,"Library":null,"Universities":[],"CourseStudents":[]},{"Id":0,"Name":"stradsdasdasing","Email":"usdsadaser@example.com","Address":null,"Laptop":null,"LibraryId":null,"Money":0,"Age":0,"Library":null,"Universities":[],"CourseStudents":[]},{"Id":0,"Name":"string","Email":"user@example.com","Address":null,"Laptop":null,"LibraryId":null,"Money":0,"Age":0,"Library":null,"Universities":[],"CourseStudents":[]}]